odoo9_addon_web_searchbar_full_width-9.0.1.0.0-py2.7-nspkg.pth
odoo_addons/web_searchbar_full_width/__openerp__.py
odoo_addons/web_searchbar_full_width/__init__.py
odoo_addons/web_searchbar_full_width/README.rst
odoo_addons/web_searchbar_full_width/views/templates.xml
odoo_addons/web_searchbar_full_width/static/description/preview.png
odoo_addons/web_searchbar_full_width/static/description/icon.png
odoo_addons/web_searchbar_full_width/static/src/css/web_searchbar_full_width.css
odoo9_addon_web_searchbar_full_width-9.0.1.0.0.dist-info/top_level.txt
odoo9_addon_web_searchbar_full_width-9.0.1.0.0.dist-info/WHEEL
odoo9_addon_web_searchbar_full_width-9.0.1.0.0.dist-info/RECORD
odoo9_addon_web_searchbar_full_width-9.0.1.0.0.dist-info/metadata.json
odoo9_addon_web_searchbar_full_width-9.0.1.0.0.dist-info/DESCRIPTION.rst
odoo9_addon_web_searchbar_full_width-9.0.1.0.0.dist-info/METADATA
odoo9_addon_web_searchbar_full_width-9.0.1.0.0.dist-info/namespace_packages.txt
